pytorch_wheel_installer/__about__.py
pytorch_wheel_installer/__init__.py
pytorch_wheel_installer/__main__.py
pytorch_wheel_installer/__version__
pytorch_wheel_installer/_tox.py
pytorch_wheel_installer/cli.py
pytorch_wheel_installer/computation_backend.py
pytorch_wheel_installer/find.py
pytorch_wheel_installer/py.typed
pytorch_wheel_installer/utils.py
pytorch_wheel_installer-0.2.1.dist-info/LICENSE
pytorch_wheel_installer-0.2.1.dist-info/METADATA
pytorch_wheel_installer-0.2.1.dist-info/WHEEL
pytorch_wheel_installer-0.2.1.dist-info/entry_points.txt
pytorch_wheel_installer-0.2.1.dist-info/top_level.txt
pytorch_wheel_installer-0.2.1.dist-info/RECORD
