Metadata-Version: 2.1
Name: pytorch-wheel-installer
Version: 0.2.1
Summary: Install PyTorch distributions from the latest wheels.
Home-page: https://github.com/pmeier/pytorch_wheel_installer
Author: Philip Meier
Author-email: github.pmeier@posteo.de
License: BSD 3-Clause
Keywords: pytorch pip wheel cli tox
Platform: UNKNOWN
Classifier: Development Status :: 7 - Inactive
Classifier: Framework :: tox
Classifier: Intended Audience :: Developers
Classifier: License :: OSI Approved :: BSD License
Classifier: Programming Language :: Python :: 3.6
Classifier: Programming Language :: Python :: 3.7
Classifier: Programming Language :: Python :: 3.8
Classifier: Topic :: System :: Installation/Setup
Classifier: Topic :: Utilities
Requires-Python: >=3.6
Requires-Dist: pip (>=20.1)
